stp_renderer/__init__.py
stp_renderer/frontend/.env
stp_renderer/frontend/.prettierrc
stp_renderer/frontend/build/asset-manifest.json
stp_renderer/frontend/build/bootstrap.min.css
stp_renderer/frontend/build/index.html
stp_renderer/frontend/build/static/js/main.3a744bc5.js
stp_renderer/frontend/build/static/js/main.3a744bc5.js.LICENSE.txt
stp_renderer/frontend/build/static/js/main.3a744bc5.js.map
stp_renderer/frontend/config-overrides.js
stp_renderer/frontend/node_modules/webassembly-interpreter/spec/.git
stp_renderer/frontend/package.json
stp_renderer/frontend/public/bootstrap.min.css
stp_renderer/frontend/public/index.html
stp_renderer/frontend/src/StpRenderer.tsx
stp_renderer/frontend/src/addShapeToScene.ts
stp_renderer/frontend/src/index.tsx
stp_renderer/frontend/src/loadGeometry.ts
stp_renderer/frontend/src/loadStpOrIgesFile.ts
stp_renderer/frontend/src/react-app-env.d.ts
stp_renderer/frontend/src/setupThreeJSViewport.ts
stp_renderer/frontend/tsconfig.json
stp_renderer/frontend/yarn.lock
streamlit_cognite_stp_renderer-0.0.1.dist-info/LICENSE
streamlit_cognite_stp_renderer-0.0.1.dist-info/METADATA
streamlit_cognite_stp_renderer-0.0.1.dist-info/WHEEL
streamlit_cognite_stp_renderer-0.0.1.dist-info/RECORD
