Metadata-Version: 2.1
Name: streamlit-cognite-stp-renderer
Version: 0.0.1
Summary: A component to render STEP files in Streamlit.
License: Apache-2.0 license
Author: Marvin Reza
Author-email: marvin.reza@cognite.com
Requires-Python: >=3.10,<4.0
Classifier: License :: Other/Proprietary License
Classifier: Programming Language :: Python :: 3
Classifier: Programming Language :: Python :: 3.10
Classifier: Programming Language :: Python :: 3.11
Classifier: Programming Language :: Python :: 3.12
Classifier: Programming Language :: Python :: 3.13
Requires-Dist: build (>=1.2.2.post1,<2.0.0)
Requires-Dist: cognite-sdk (>=7.51.1,<8.0.0)
Requires-Dist: streamlit (==1.39.0)
